sfextract/__init__.py
sfextract/blast.py
sfextract/main.py
sfextract/setupfactory7.py
sfextract/setupfactory8.py
sfextract-0.0.8.dist-info/LICENCE.md
sfextract-0.0.8.dist-info/METADATA
sfextract-0.0.8.dist-info/WHEEL
sfextract-0.0.8.dist-info/entry_points.txt
sfextract-0.0.8.dist-info/top_level.txt
sfextract-0.0.8.dist-info/RECORD
