Metadata-Version: 2.1
Name: sfextract
Version: 0.0.8
Summary: sfextract tries to extract Setup Factory files on any OS.
Author: gdesmar
Project-URL: Homepage, https://github.com/CybercentreCanada/sfextract
Project-URL: Bug Tracker, https://github.com/CybercentreCanada/sfextract/issues
Classifier: Programming Language :: Python :: 3
Classifier: License :: OSI Approved :: MIT License
Classifier: Operating System :: OS Independent
Classifier: Environment :: Console
Classifier: Topic :: File Formats
Classifier: Topic :: System :: Archiving
Classifier: Topic :: System :: Installation/Setup
Requires-Python: >=3.8
License-File: LICENCE.md
Requires-Dist: pefile
